setup.py
Lysort/Lysort.py
Lysort/__init__.py
Lysort.egg-info/PKG-INFO
Lysort.egg-info/SOURCES.txt
Lysort.egg-info/dependency_links.txt
Lysort.egg-info/top_level.txt