Metadata-Version: 1.0
Name: Lysort
Version: 0.1.0
Summary: There have Six sort functions to sort data
Home-page: https://github.com/bookisLY/Lysort
Author: bookist123
Author-email: 421736951@qq.com
License: MIT
Platform: UNKNOWN
